Metadata-Version: 2.1
Name: masterfile
Version: 0.5.0
Summary: Tools to organize, document, and validate the variables of interest in scientific studies
Home-page: https://github.com/uwmadison-chm/masterfile
Author: Nate Vack
Author-email: njvack@wisc.edu
Maintainer: Nate Vack
Maintainer-email: njvack@wisc.edu
License: MIT License
Download-URL: https://github.com/uwmadison-chm/masterfile/releases
Keywords: science research data library
Platform: OS Independent
Classifier: Development Status :: 4 - Beta
Classifier: Environment :: Console
Classifier: Intended Audience :: Science/Research
Classifier: License :: OSI Approved :: MIT License
Classifier: Natural Language :: English
Classifier: Operating System :: OS Independent
Classifier: Programming Language :: Python
Classifier: Topic :: Scientific/Engineering :: Information Analysis
Provides: masterfile
Requires-Dist: pandas (>=0.9)
Requires-Dist: attrs (>=17.0)
Requires-Dist: schema (>=0.2)
